cucumber_messages/__init__.py
cucumber_messages/_message_enums.py
cucumber_messages/_messages.py
cucumber_messages/json_converter.py
cucumber_messages-32.0.1.dist-info/licenses/LICENSE
cucumber_messages-32.0.1.dist-info/WHEEL
cucumber_messages-32.0.1.dist-info/METADATA
cucumber_messages-32.0.1.dist-info/RECORD
