Metadata-Version: 2.4
Name: cucumber-messages
Version: 32.0.1
Summary: Cucumber Messages is a message protocol for representing results and other information from Cucumber. 
Keywords: gherkin,cucumber,bdd
Author: Cucumber Limited
Author-email: Cucumber Limited <cukes@googlegroups.com>
License-Expression: MIT
License-File: LICENSE
Classifier: Development Status :: 4 - Beta
Classifier: Intended Audience :: Developers
Classifier: License :: OSI Approved :: MIT License
Classifier: Operating System :: POSIX
Classifier: Operating System :: Microsoft :: Windows
Classifier: Operating System :: MacOS :: MacOS X
Classifier: Topic :: Software Development :: Testing
Classifier: Topic :: Utilities
Classifier: Programming Language :: Python :: 3
Classifier: Programming Language :: Python :: 3.9
Classifier: Programming Language :: Python :: 3.10
Classifier: Programming Language :: Python :: 3.11
Classifier: Programming Language :: Python :: 3.12
Classifier: Programming Language :: Python :: 3.13
Maintainer: Konstantin Goloveshko
Maintainer-email: Konstantin Goloveshko <kostya.goloveshko@gmail.com>
Requires-Python: >=3.9
Project-URL: Changelog, https://github.com/cucumber/messages/releases
Project-URL: Download, https://pypi.org/project/cucumber-messages
Project-URL: Homepage, https://github.com/cucumber/messages
Project-URL: Issues, https://github.com/cucumber/messages/issues
Project-URL: Repository, https://github.com/cucumber/messages.git
